{
  "version": "7",
  "dialect": "postgresql",
  "entries": [
    {
      "idx": 0,
      "version": "7",
      "when": 1773608111310,
      "tag": "0000_mushy_black_bolt",
      "breakpoints": true
    },
    {
      "idx": 1,
      "version": "7",
      "when": 1773611003731,
      "tag": "0001_loose_young_avengers",
      "breakpoints": true
    },
    {
      "idx": 2,
      "version": "7",
      "when": 1773620692758,
      "tag": "0002_thin_mathemanic",
      "breakpoints": true
    },
    {
      "idx": 3,
      "version": "7",
      "when": 1773711664897,
      "tag": "0003_lovely_princess_powerful",
      "breakpoints": true
    },
    {
      "idx": 4,
      "version": "7",
      "when": 1774000000000,
      "tag": "0004_progress_checkins",
      "breakpoints": true
    },
    {
      "idx": 5,
      "version": "7",
      "when": 1774100000000,
      "tag": "0005_whitelist",
      "breakpoints": true
    },
    {
      "idx": 6,
      "version": "7",
      "when": 1774200000000,
      "tag": "0006_chunky_thunderbird",
      "breakpoints": true
    },
    {
      "idx": 7,
      "version": "7",
      "when": 1774300000000,
      "tag": "0007_lp_draft",
      "breakpoints": true
    }
  ]
}